jnews_mcp_server/__init__.py
jnews_mcp_server/__main__.py
jnews_mcp_server/server.py
jnews_mcp_server-0.1.3.dist-info/METADATA
jnews_mcp_server-0.1.3.dist-info/WHEEL
jnews_mcp_server-0.1.3.dist-info/entry_points.txt
jnews_mcp_server-0.1.3.dist-info/RECORD
