Metadata-Version: 2.4
Name: jnews-mcp-server
Version: 0.1.3
Summary: 一个提供热点新闻头条信息功能的模型上下文协议（Model Context Protocol）服务器。
Author-email: juhemcp <dev@juheapi.com>
Requires-Python: >=3.10
Requires-Dist: mcp[cli]>=1.4.1
